mercadoradar/__init__.py
mercadoradar/_client.py
mercadoradar/models/_account.py
mercadoradar/models/_attribute_type.py
mercadoradar/models/_attribute_value.py
mercadoradar/models/_brand.py
mercadoradar/models/_category.py
mercadoradar/models/_filter.py
mercadoradar/models/_paginated_response.py
mercadoradar/models/_product.py
mercadoradar/models/_product_attribute_value.py
mercadoradar/models/_product_history.py
mercadoradar/models/_search.py
mercadoradar/models/_seller.py
mercadoradar/models/_site.py
mercadoradar/models/_ticket.py
mercadoradar/models/_user.py
mercadoradar/models/_verification_history.py
mercadoradar/resources/_account.py
mercadoradar/resources/_attribute_type.py
mercadoradar/resources/_attribute_value.py
mercadoradar/resources/_brand.py
mercadoradar/resources/_category.py
mercadoradar/resources/_filter.py
mercadoradar/resources/_product.py
mercadoradar/resources/_product_attribute_value.py
mercadoradar/resources/_product_history.py
mercadoradar/resources/_search.py
mercadoradar/resources/_seller.py
mercadoradar/resources/_site.py
mercadoradar/resources/_ticket.py
mercadoradar/resources/_user.py
mercadoradar/resources/_verification_history.py
mercadoradar-2.2.9.dist-info/METADATA
mercadoradar-2.2.9.dist-info/WHEEL
mercadoradar-2.2.9.dist-info/top_level.txt
mercadoradar-2.2.9.dist-info/RECORD
