Metadata-Version: 2.2
Name: mercadoradar
Version: 2.2.9
Summary: Python client library for Mercado Radar API
Author-email: Mercado Radar <dev@mercadoradar.com.br>
License: MIT
Project-URL: Documentation, https://mercadoradar.readme.io/
Project-URL: Homepage, https://www.mercadoradar.com.br/?utm_source=pip
Keywords: mercadoradar,mercadoradar-sdk
Requires-Python: <4,>=3.10.6
Requires-Dist: h2<5.0.0,>=4.2.0
Requires-Dist: httpx<0.29.0,>=0.28.1
Requires-Dist: pydantic<3.0.0,>=2.10.6
Provides-Extra: dev
Requires-Dist: jinja2<4.0.0,>=3.1.5; extra == "dev"
